Metadata-Version: 1.1
Name: fixerio3
Version: 0.1.0
Summary: A python3 API to interact with the fixer.io foreign exchange rates and currency conversion JSON API
Home-page: https://github.com/saporitigianni/fixerio3
Author: Gianni Saporiti
Author-email: saporitigianni@outlook.com
License: MIT
Keywords: forex,api,currencies,financial
Platform: UNKNOWN
Classifier: Development Status :: 4 - Beta
Classifier: Intended Audience :: Developers
Classifier: Intended Audience :: Financial and Insurance Industry
Classifier: License :: OSI Approved :: MIT License
Classifier: Operating System :: OS Independent
Classifier: Programming Language :: Python :: 3
Classifier: Topic :: Office/Business :: Financial
Classifier: Topic :: Software Development :: Build Tools
